ghj/__init__.py
ghj/dash.py
ghj/fetch.py
ghj/ghj_cli.py
ghj/hugo.py
ghj/set.py
ghj/stats.py
ghj/utils.py
gh_json-0.1.0.dist-info/LICENSE
gh_json-0.1.0.dist-info/METADATA
gh_json-0.1.0.dist-info/WHEEL
gh_json-0.1.0.dist-info/entry_points.txt
gh_json-0.1.0.dist-info/top_level.txt
gh_json-0.1.0.dist-info/RECORD
