Metadata-Version: 2.2
Name: gh-json
Version: 0.1.0
Summary: A toolkit to work with GitHub repositories, generating JSON data and more
Home-page: https://github.com/queelius/ghj
Author: Alex Towell
Author-email: lex@metafunctor.com
License: MIT
Classifier: Programming Language :: Python :: 3
Classifier: License :: OSI Approved :: MIT License
Classifier: Operating System :: OS Independent
Requires-Python: >=3.6
License-File: LICENSE
Requires-Dist: click>=8.0.0
Requires-Dist: rich>=10.0.0
Requires-Dist: requests
Requires-Dist: pyyaml
Requires-Dist: jmespath
Requires-Dist: streamlit
Requires-Dist: jaf
